zrq/__init__.py
zrq-0.1a0.dist-info/METADATA
zrq-0.1a0.dist-info/WHEEL
zrq-0.1a0.dist-info/top_level.txt
zrq-0.1a0.dist-info/RECORD
